joshuaproject/__init__.py
joshuaproject/_nbdev.py
joshuaproject/core.py
joshuaproject/countrycodes.py
joshuaproject-0.0.5.dist-info/LICENSE
joshuaproject-0.0.5.dist-info/METADATA
joshuaproject-0.0.5.dist-info/WHEEL
joshuaproject-0.0.5.dist-info/entry_points.txt
joshuaproject-0.0.5.dist-info/top_level.txt
joshuaproject-0.0.5.dist-info/RECORD
