Metadata-Version: 2.1
Name: joshuaproject
Version: 0.0.5
Summary: Python library for JoshuaProject.net
Home-page: https://github.com/kdorichev/joshuaproject
Author: Konstantin Dorichev
Author-email: kdorichev@gmail.com
License: Apache Software License 2.0
Keywords: python,library
Platform: UNKNOWN
Classifier: Development Status :: 3 - Alpha
Classifier: Intended Audience :: Developers
Classifier: License :: OSI Approved :: Apache Software License
Classifier: Natural Language :: English
Classifier: Programming Language :: Python :: 3.6
Classifier: Programming Language :: Python :: 3.7
Classifier: Programming Language :: Python :: 3.8
Requires-Python: >=3.6
Requires-Dist: urllib3
Requires-Dist: certifi
Requires-Dist: datetime
Requires-Dist: pandas
